plenoptic/__init__.py
plenoptic/data/__init__.py
plenoptic/data/color_wheel.jpg
plenoptic/data/curie.pgm
plenoptic/data/einstein.pgm
plenoptic/data/fetch.py
plenoptic/data/parrot.png
plenoptic/data/reptile_skin.pgm
plenoptic/metric/DN_filts.npy
plenoptic/metric/DN_sigmas.npy
plenoptic/metric/__init__.py
plenoptic/metric/classes.py
plenoptic/metric/model_metric.py
plenoptic/metric/naive.py
plenoptic/metric/perceptual_distance.py
plenoptic/simulate/__init__.py
plenoptic/simulate/canonical_computations/__init__.py
plenoptic/simulate/canonical_computations/filters.py
plenoptic/simulate/canonical_computations/laplacian_pyramid.py
plenoptic/simulate/canonical_computations/non_linearities.py
plenoptic/simulate/canonical_computations/steerable_pyramid_freq.py
plenoptic/simulate/models/__init__.py
plenoptic/simulate/models/frontend.py
plenoptic/simulate/models/naive.py
plenoptic/simulate/models/portilla_simoncelli.py
plenoptic/synthesize/__init__.py
plenoptic/synthesize/autodiff.py
plenoptic/synthesize/eigendistortion.py
plenoptic/synthesize/mad_competition.py
plenoptic/synthesize/metamer.py
plenoptic/synthesize/synthesis.py
plenoptic/tools/__init__.py
plenoptic/tools/conv.py
plenoptic/tools/convergence.py
plenoptic/tools/data.py
plenoptic/tools/display.py
plenoptic/tools/external.py
plenoptic/tools/io.py
plenoptic/tools/optim.py
plenoptic/tools/signal.py
plenoptic/tools/stats.py
plenoptic/tools/validate.py
plenoptic-1.3.1.dist-info/licenses/LICENSE
plenoptic-1.3.1.dist-info/METADATA
plenoptic-1.3.1.dist-info/WHEEL
plenoptic-1.3.1.dist-info/top_level.txt
plenoptic-1.3.1.dist-info/RECORD
