Metadata-Version: 2.4
Name: plenoptic
Version: 1.3.1
Summary: Python library for model-based stimulus synthesis.
Author: Plenoptic authors
Project-URL: Homepage, https://github.com/plenoptic-org/plenoptic
Project-URL: Documentation, https://docs.plenoptic.org
Project-URL: Download, https://zenodo.org/doi/10.5281/zenodo.10151130
Keywords: neuroscience,pytorch,visual information processing,machine learning,explainability,computational models
Classifier: Development Status :: 5 - Production/Stable
Classifier: Programming Language :: Python :: 3.10
Classifier: Programming Language :: Python :: 3.11
Classifier: Programming Language :: Python :: 3.12
Classifier: License :: OSI Approved :: MIT License
Classifier: Intended Audience :: Science/Research
Requires-Python: >=3.10
License-File: LICENSE
Requires-Dist: numpy>=1.1
Requires-Dist: torch!=1.12.0,>=1.8
Requires-Dist: pyrtools>=1.0.9
Requires-Dist: scipy>=1.0
Requires-Dist: matplotlib>=3.3
Requires-Dist: tqdm>=4.29
Requires-Dist: imageio>=2.5
Requires-Dist: scikit-image>=0.15.0
Requires-Dist: einops>=0.3.0
Requires-Dist: importlib-resources>=6.0
Requires-Dist: Deprecated
Provides-Extra: docs
Requires-Dist: sphinx; extra == "docs"
Requires-Dist: sphinx_rtd_theme>=1.3.0rc1; extra == "docs"
Requires-Dist: numpydoc; extra == "docs"
Requires-Dist: sphinxcontrib-apidoc; extra == "docs"
Requires-Dist: sphinx-autodoc-typehints; extra == "docs"
Requires-Dist: sphinx-copybutton; extra == "docs"
Requires-Dist: myst-parser; extra == "docs"
Requires-Dist: sphinxcontrib-bibtex; extra == "docs"
Requires-Dist: sphinx-design; extra == "docs"
Requires-Dist: pooch; extra == "docs"
Requires-Dist: myst-nb; extra == "docs"
Requires-Dist: ipywidgets; extra == "docs"
Requires-Dist: torchvision; extra == "docs"
Requires-Dist: pooch; extra == "docs"
Requires-Dist: jupytext; extra == "docs"
Requires-Dist: sphobjinv; extra == "docs"
Requires-Dist: sphinx-togglebutton; extra == "docs"
Provides-Extra: test
Requires-Dist: pytest>=5.1.2; extra == "test"
Requires-Dist: pytest-cov; extra == "test"
Requires-Dist: pytest-xdist; extra == "test"
Requires-Dist: pytest-order; extra == "test"
Requires-Dist: pooch>=1.2.0; extra == "test"
Requires-Dist: torchvision; extra == "test"
Provides-Extra: lint
Requires-Dist: ruff>=0.6.8; extra == "lint"
Requires-Dist: numpydoc; extra == "lint"
Provides-Extra: dev
Requires-Dist: plenoptic[lint,test]; extra == "dev"
Provides-Extra: nb
Requires-Dist: jupyter; extra == "nb"
Requires-Dist: ipywidgets; extra == "nb"
Requires-Dist: nbclient>=0.5.5; extra == "nb"
Requires-Dist: torchvision>=0.3; extra == "nb"
Requires-Dist: pooch>=1.2.0; extra == "nb"
Requires-Dist: jupytext; extra == "nb"
Dynamic: license-file
